rllm/__init__.py
reallm-0.1.0.dist-info/METADATA
reallm-0.1.0.dist-info/WHEEL
reallm-0.1.0.dist-info/licenses/LICENSE
reallm-0.1.0.dist-info/RECORD
