Metadata-Version: 2.4
Name: reallm
Version: 0.1.0
Summary: Reinforcement Agent Learning Language Model
Author-email: Teïlo Millet <teilo.millet@gmail.com>
License: Apache 2.0
License-File: LICENSE
Requires-Python: >=3.8
